rejected_article_tracker/__init__.py
rejected_article_tracker/data/fake_rejected_articles.xlsx
rejected_article_tracker/src/ArticleItem.py
rejected_article_tracker/src/AuthorNames.py
rejected_article_tracker/src/BestCandidate.py
rejected_article_tracker/src/ConfigChecker.py
rejected_article_tracker/src/CrossRef.py
rejected_article_tracker/src/EmptyResult.py
rejected_article_tracker/src/FilteredArticles.py
rejected_article_tracker/src/LoadModel.py
rejected_article_tracker/src/ManuscriptIdRaw.py
rejected_article_tracker/src/RejectedArticlesMatch.py
rejected_article_tracker/src/Result.py
rejected_article_tracker/src/ScholarOneArticleAdapter.py
rejected_article_tracker/src/ScholarOneRejectedArticlesMatch.py
rejected_article_tracker/src/SearchProvider.py
rejected_article_tracker/src/SearchResult.py
rejected_article_tracker/src/__init__.py
rejected_article_tracker/src/ML/ArXivArticleItem.py
rejected_article_tracker/src/ML/ArXivAuthorNames.py
rejected_article_tracker/src/ML/ArXivFilteredArticles.py
rejected_article_tracker/src/ML/ArXivManuscriptIdRaw.py
rejected_article_tracker/src/ML/ArXivOAIPMH.py
rejected_article_tracker/src/ML/ArXivOAIPMHRecord.py
rejected_article_tracker/src/ML/ArXivTrainingData.py
rejected_article_tracker/src/ML/CleanTrainingData.py
rejected_article_tracker/src/ML/CrossRefDOIData.py
rejected_article_tracker/src/ML/CrossRefEarliestDate.py
rejected_article_tracker/src/ML/CrossRefSearch.py
rejected_article_tracker/src/ML/CrossRefTrainingData.py
rejected_article_tracker/src/ML/CrossRefUtils.py
rejected_article_tracker/src/ML/CrossRefWorksRecord.py
rejected_article_tracker/src/ML/Train.py
rejected_article_tracker/src/ML/TrainingData.py
rejected_article_tracker/src/ML/TrainingRow.py
rejected_article_tracker/src/ML/__init__.py
rejected_article_tracker/src/ML/config.py
rejected_article_tracker/src/ML/small_models/__init__.py
rejected_article_tracker/src/ML/small_models/lr_model
rejected_article_tracker/tests/__init__.py
rejected_article_tracker-1.5.13.dist-info/LICENSE.md
rejected_article_tracker-1.5.13.dist-info/METADATA
rejected_article_tracker-1.5.13.dist-info/WHEEL
rejected_article_tracker-1.5.13.dist-info/top_level.txt
rejected_article_tracker-1.5.13.dist-info/RECORD
