Metadata-Version: 2.1
Name: rejected-article-tracker
Version: 1.5.13
Summary: Utility package to track if a journal article has been published somewhere.
Home-page: https://github.com/sagepublishing/rejected_article_tracker_pkg
Author: Andy Hails
Author-email: andy.hails@sagepub.co.uk
License: UNKNOWN
Platform: UNKNOWN
Classifier: Programming Language :: Python :: 3
Classifier: License :: OSI Approved :: MIT License
Classifier: Operating System :: OS Independent
License-File: LICENSE.md
Requires-Dist: scikit-learn (==1.0.2)
Requires-Dist: markdown
Requires-Dist: pandas
Requires-Dist: openpyxl
Requires-Dist: xlsxwriter
Requires-Dist: fuzzywuzzy
Requires-Dist: requests
Requires-Dist: oaiharvest
Requires-Dist: langdetect
Requires-Dist: gensim
Requires-Dist: numpy
Requires-Dist: python-Levenshtein
Requires-Dist: tqdm
Requires-Dist: xmltodict
